Esipraisal/Appraisal.py
Esipraisal/Esipraisal.py
Esipraisal/__init__.py
Esipraisal/esi.py
Esipraisal-0.0.2.dist-info/LICENSE
Esipraisal-0.0.2.dist-info/METADATA
Esipraisal-0.0.2.dist-info/WHEEL
Esipraisal-0.0.2.dist-info/top_level.txt
Esipraisal-0.0.2.dist-info/RECORD
