Metadata-Version: 2.1
Name: Esipraisal
Version: 0.0.2
Summary: An Eve Online appraisal tool which uses ESI
Home-page: https://github.com/FlyingKiwis/Esipraisal
Author: Flying Kiwi
Author-email: github@flyingkiwibird.com
License: MIT
Keywords: Esi Eve Python Api
Platform: UNKNOWN
Classifier: Development Status :: 3 - Alpha
Classifier: Intended Audience :: Developers
Classifier: Topic :: Utilities
Classifier: Programming Language :: Python
Classifier: Programming Language :: Python :: 3.3
Classifier: Programming Language :: Python :: 3.4
Classifier: Programming Language :: Python :: 3.5
Classifier: Programming Language :: Python :: 3.6
Requires-Dist: EsiPysi (==0.9.1)
Requires-Dist: numpy (==1.18.4)
